odoo/addons/pms_contract/README.rst
odoo/addons/pms_contract/__init__.py
odoo/addons/pms_contract/__manifest__.py
odoo/addons/pms_contract/i18n/es.po
odoo/addons/pms_contract/i18n/pms_contract.pot
odoo/addons/pms_contract/models/__init__.py
odoo/addons/pms_contract/models/contract_contract.py
odoo/addons/pms_contract/models/contract_line.py
odoo/addons/pms_contract/models/pms_property.py
odoo/addons/pms_contract/models/pms_service.py
odoo/addons/pms_contract/readme/CONFIGURE.rst
odoo/addons/pms_contract/readme/CONTRIBUTORS.rst
odoo/addons/pms_contract/readme/DESCRIPTION.rst
odoo/addons/pms_contract/readme/USAGE.rst
odoo/addons/pms_contract/static/description/icon.png
odoo/addons/pms_contract/static/description/index.html
odoo/addons/pms_contract/views/contract_contract.xml
odoo/addons/pms_contract/views/menu.xml
odoo/addons/pms_contract/views/pms_property.xml
odoo/addons/pms_contract/views/pms_service.xml
odoo14_addon_pms_contract-14.0.1.0.1.dev2.dist-info/METADATA
odoo14_addon_pms_contract-14.0.1.0.1.dev2.dist-info/WHEEL
odoo14_addon_pms_contract-14.0.1.0.1.dev2.dist-info/top_level.txt
odoo14_addon_pms_contract-14.0.1.0.1.dev2.dist-info/RECORD
